snakemake_storage_plugin_zenodo/__init__.py
snakemake_storage_plugin_zenodo/helper.py
snakemake_storage_plugin_zenodo-0.1.5.dist-info/LICENSE
snakemake_storage_plugin_zenodo-0.1.5.dist-info/METADATA
snakemake_storage_plugin_zenodo-0.1.5.dist-info/WHEEL
snakemake_storage_plugin_zenodo-0.1.5.dist-info/RECORD
